{
  "test-user-001": {
    "userId": "test-user-001",
    "createdAt": "2026-06-05T11:29:51.018Z",
    "lastSeen": "2026-06-05T11:29:51.032Z",
    "totalSessions": 1,
    "disc": {
      "sessions": [],
      "primary": null,
      "secondary": null,
      "feelingColor": null,
      "stressColor": null,
      "confidence": 0
    },
    "kernkwadranten": {
      "sessions": [],
      "topQualities": [],
      "routesCompleted": 0
    },
    "waarden": null,
    "rondes": [
      {
        "date": "2026-06-05T11:29:51.024Z",
        "caseId": "D1_TENSION_001",
        "domain": "D1",
        "caseType": "tension",
        "tags": {
          "needs.attention": 2,
          "protections.withdraw": 2,
          "sensitive_points.not_seen": 1
        },
        "modus": "solo",
        "koppelCode": null
      }
    ],
    "tagScores": {
      "needs": {
        "needs.attention": 2
      },
      "protections": {
        "protections.withdraw": 3
      },
      "sensitive_points": {
        "sensitive_points.not_seen": 1.5
      },
      "patterns": {},
      "skills": {},
      "centers": {},
      "domains": {
        "D1": 1
      }
    },
    "topBehoeften": [
      {
        "key": "needs.attention",
        "label": "Aandacht",
        "score": 2
      }
    ],
    "topBeschermingen": [
      {
        "key": "protections.withdraw",
        "label": "Terugtrekken",
        "score": 3
      }
    ],
    "topGevoeligePlekken": [
      {
        "key": "sensitive_points.not_seen",
        "label": "Niet gezien worden",
        "score": 1.5
      }
    ],
    "topPatronen": [],
    "topSkills": [],
    "sterkeDomainen": [],
    "groeiDomainen": [
      "D1"
    ],
    "enneagramSignalen": {},
    "traits": {
      "directness": null,
      "expressiveness": null,
      "steadiness": null,
      "precision": null
    },
    "patterns": {
      "decisionStyle": null,
      "conflictStyle": null,
      "communicationStyle": null,
      "stressPattern": null
    },
    "recognizedThemas": [],
    "insights": [
      "Je sterkste behoefte in relaties lijkt Aandacht te zijn.",
      "Je meest gebruikte bescherming is Terugtrekken. Dit probeert iets waardevols te bewaken."
    ],
    "report": null,
    "accountId": null
  }
}